{
    "adelaide": {
        "direction": "horizontal",
        "colours": [
            "blue",
            "red",
            "yellow"
        ]
    },
    "brisbane": {
        "direction": "horizontal",
        "colours": [
            "maroon",
            "gold",
            "blue"
        ]
    },
    "carlton": {
        "direction": "horizontal",
        "colours": [
            "navy",
            "navy"
        ]
    },
    "collingwood": {
        "direction": "vertical",
        "colours": [
            "black",
            "white"
        ]
    },
    "essendon": {
        "direction": "diagonal",
        "colours": [
            "red",
            "black"
        ]
    },
    "fremantle": {
        "direction": "horizontal",
        "colours": [
            "purple",
            "white"
        ]
    },
    "geelong": {
        "direction": "vertical",
        "colours": [
            "white",
            "darkblue"
        ]
    },
    "goldcoast": {
        "direction": "diagonal",
        "colours": [
            "red",
            "yellow"
        ]
    },
    "gws": {
        "direction": "horizontal",
        "colours": [
            "orange",
            "orange"
        ]
    },
    "hawthorn": {
        "direction": "vertical",
        "colours": [
            "brown",
            "yellow"
        ]
    },
    "melbourne": {
        "direction": "horizontal",
        "colours": [
            "red",
            "blue"
        ]
    },
    "northmelbourne": {
        "direction": "vertical",
        "colours": [
            "blue",
            "white"
        ]
    },
    "portadelaide": {
        "direction": "vertical",
        "colours": [
            "teal",
            "black",
            "white"
        ]
    },
    "richmond": {
        "direction": "diagonal",
        "colours": [
            "yellow",
            "black"
        ]
    },
    "stkilda": {
        "direction": "vertical",
        "colours": [
            "red",
            "white",
            "black"
        ]
    },
    "sydney": {
        "direction": "horizontal",
        "colours": [
            "red",
            "white"
        ]
    },
    "westcoast": {
        "direction": "vertical",
        "colours": [
            "yellow",
            "blue",
            "yellow"
        ]
    },
    "westernbulldogs": {
        "direction": "horizontal",
        "colours": [
            "white",
            "blue",
            "red"
        ]
    }
}